{
  "item": [
    {
      "id": "f051ef2d-37d5-4408-b1ab-291d220b3e68",
      "name": "Validate",
      "description": {
        "content": "",
        "type": "text/plain"
      },
      "item": [
        {
          "id": "28dc3f07-b9d1-48a9-a3b3-0f44a3b6ea0c",
          "name": "Validate an AsyncAPI document",
          "request": {
            "name": "Validate an AsyncAPI document",
            "description": {},
            "url": {
              "path": [
                "validate"
              ],
              "host": [
                "{{baseUrl}}"
              ],
              "query": [],
              "variable": []
            },
            "header": [
              {
                "key": "Content-Type",
                "value": "application/json"
              },
              {
                "key": "Accept",
                "value": "application/problem+json"
              }
            ],
            "method": "POST",
            "auth": null,
            "body": {
              "mode": "raw",
              "raw": "{\n  \"asyncapi\": \"<object>\"\n}",
              "options": {
                "raw": {
                  "language": "json"
                }
              }
            }
          },
          "response": [
            {
              "id": "a5517836-ba56-4243-83ba-a2bfa413a37a",
              "name": "Document is valid",
              "originalRequest": {
                "url": {
                  "path": [
                    "validate"
                  ],
                  "host": [
                    "{{baseUrl}}"
                  ],
                  "query": [],
                  "variable": []
                },
                "method": "POST",
                "body": {
                  "mode": "raw",
                  "raw": "{\n  \"asyncapi\": \"<object>\"\n}",
                  "options": {
                    "raw": {
                      "language": "json"
                    }
                  }
                }
              },
              "status": "No Content",
              "code": 204,
              "header": [
                {
                  "key": "Content-Type",
                  "value": "text/plain"
                }
              ],
              "body": "",
              "cookie": [],
              "_postman_previewlanguage": "text"
            },
            {
              "id": "8d593742-eca2-45b5-a84e-a6898ad96747",
              "name": "RFC 7807 problem response",
              "originalRequest": {
                "url": {
                  "path": [
                    "validate"
                  ],
                  "host": [
                    "{{baseUrl}}"
                  ],
                  "query": [],
                  "variable": []
                },
                "header": [
                  {
                    "key": "Accept",
                    "value": "application/problem+json"
                  }
                ],
                "method": "POST",
                "body": {
                  "mode": "raw",
                  "raw": "{\n  \"asyncapi\": \"<object>\"\n}",
                  "options": {
                    "raw": {
                      "language": "json"
                    }
                  }
                }
              },
              "status": "Bad Request",
              "code": 400,
              "header": [
                {
                  "key": "Content-Type",
                  "value": "application/problem+json"
                }
              ],
              "body": "{\n  \"type\": \"https://AvorCmBazGYDsnzuMDYNlJYkSGB.bhcmStac\",\n  \"title\": \"string\",\n  \"status\": 7198,\n  \"detail\": \"string\",\n  \"instance\": \"string\"\n}",
              "cookie": [],
              "_postman_previewlanguage": "json"
            },
            {
              "id": "68ac459a-7ad1-4e6b-ad47-5249c27b3420",
              "name": "RFC 7807 problem response",
              "originalRequest": {
                "url": {
                  "path": [
                    "validate"
                  ],
                  "host": [
                    "{{baseUrl}}"
                  ],
                  "query": [],
                  "variable": []
                },
                "header": [
                  {
                    "key": "Accept",
                    "value": "application/problem+json"
                  }
                ],
                "method": "POST",
                "body": {
                  "mode": "raw",
                  "raw": "{\n  \"asyncapi\": \"<object>\"\n}",
                  "options": {
                    "raw": {
                      "language": "json"
                    }
                  }
                }
              },
              "status": "Unprocessable Entity (WebDAV) (RFC 4918)",
              "code": 422,
              "header": [
                {
                  "key": "Content-Type",
                  "value": "application/problem+json"
                }
              ],
              "body": "{\n  \"type\": \"https://AvorCmBazGYDsnzuMDYNlJYkSGB.bhcmStac\",\n  \"title\": \"string\",\n  \"status\": 7198,\n  \"detail\": \"string\",\n  \"instance\": \"string\"\n}",
              "cookie": [],
              "_postman_previewlanguage": "json"
            }
          ],
          "event": [],
          "protocolProfileBehavior": {
            "disableBodyPruning": true
          }
        }
      ],
      "event": []
    },
    {
      "id": "7bbc5fd6-a5b0-4727-baaa-194e70eb744f",
      "name": "Parse",
      "description": {
        "content": "",
        "type": "text/plain"
      },
      "item": [
        {
          "id": "ee9402ff-0607-4139-87da-87a9ae8dc3a6",
          "name": "Parse an AsyncAPI document",
          "request": {
            "name": "Parse an AsyncAPI document",
            "description": {},
            "url": {
              "path": [
                "parse"
              ],
              "host": [
                "{{baseUrl}}"
              ],
              "query": [],
              "variable": []
            },
            "header": [
              {
                "key": "Content-Type",
                "value": "application/json"
              },
              {
                "key": "Accept",
                "value": "application/json"
              }
            ],
            "method": "POST",
            "auth": null,
            "body": {
              "mode": "raw",
              "raw": "{\n  \"asyncapi\": \"<object>\"\n}",
              "options": {
                "raw": {
                  "language": "json"
                }
              }
            }
          },
          "response": [
            {
              "id": "8b4e4708-1b52-404b-959e-e15daf082d29",
              "name": "Parsed document",
              "originalRequest": {
                "url": {
                  "path": [
                    "parse"
                  ],
                  "host": [
                    "{{baseUrl}}"
                  ],
                  "query": [],
                  "variable": []
                },
                "header": [
                  {
                    "key": "Accept",
                    "value": "application/json"
                  }
                ],
                "method": "POST",
                "body": {
                  "mode": "raw",
                  "raw": "{\n  \"asyncapi\": \"<object>\"\n}",
                  "options": {
                    "raw": {
                      "language": "json"
                    }
                  }
                }
              },
              "status": "OK",
              "code": 200,
              "header": [
                {
                  "key": "Content-Type",
                  "value": "application/json"
                }
              ],
              "body": "{\n  \"parsed\": \"string\"\n}",
              "cookie": [],
              "_postman_previewlanguage": "json"
            },
            {
              "id": "efb5f67e-dea6-429e-93d2-8163d9a203ac",
              "name": "RFC 7807 problem response",
              "originalRequest": {
                "url": {
                  "path": [
                    "parse"
                  ],
                  "host": [
                    "{{baseUrl}}"
                  ],
                  "query": [],
                  "variable": []
                },
                "header": [
                  {
                    "key": "Accept",
                    "value": "application/problem+json"
                  }
                ],
                "method": "POST",
                "body": {
                  "mode": "raw",
                  "raw": "{\n  \"asyncapi\": \"<object>\"\n}",
                  "options": {
                    "raw": {
                      "language": "json"
                    }
                  }
                }
              },
              "status": "Unprocessable Entity (WebDAV) (RFC 4918)",
              "code": 422,
              "header": [
                {
                  "key": "Content-Type",
                  "value": "application/problem+json"
                }
              ],
              "body": "{\n  \"type\": \"https://AvorCmBazGYDsnzuMDYNlJYkSGB.bhcmStac\",\n  \"title\": \"string\",\n  \"status\": 7198,\n  \"detail\": \"string\",\n  \"instance\": \"string\"\n}",
              "cookie": [],
              "_postman_previewlanguage": "json"
            }
          ],
          "event": [],
          "protocolProfileBehavior": {
            "disableBodyPruning": true
          }
        }
      ],
      "event": []
    },
    {
      "id": "97e62b58-174d-4597-b2f1-0cbd93545ca0",
      "name": "Convert",
      "description": {
        "content": "",
        "type": "text/plain"
      },
      "item": [
        {
          "id": "4df19ee0-ed28-45fd-86c6-d5dd094a9adb",
          "name": "Convert an AsyncAPI document to another version or format",
          "request": {
            "name": "Convert an AsyncAPI document to another version or format",
            "description": {},
            "url": {
              "path": [
                "convert"
              ],
              "host": [
                "{{baseUrl}}"
              ],
              "query": [],
              "variable": []
            },
            "header": [
              {
                "key": "Content-Type",
                "value": "application/json"
              },
              {
                "key": "Accept",
                "value": "application/json"
              }
            ],
            "method": "POST",
            "auth": null,
            "body": {
              "mode": "raw",
              "raw": "{\n  \"asyncapi\": \"<object>\",\n  \"version\": \"<string>\",\n  \"language\": \"<string>\"\n}",
              "options": {
                "raw": {
                  "language": "json"
                }
              }
            }
          },
          "response": [
            {
              "id": "7ab7c02a-8108-49b3-9160-d4805588b963",
              "name": "Converted document",
              "originalRequest": {
                "url": {
                  "path": [
                    "convert"
                  ],
                  "host": [
                    "{{baseUrl}}"
                  ],
                  "query": [],
                  "variable": []
                },
                "header": [
                  {
                    "key": "Accept",
                    "value": "application/json"
                  }
                ],
                "method": "POST",
                "body": {
                  "mode": "raw",
                  "raw": "{\n  \"asyncapi\": \"<object>\",\n  \"version\": \"<string>\",\n  \"language\": \"<string>\"\n}",
                  "options": {
                    "raw": {
                      "language": "json"
                    }
                  }
                }
              },
              "status": "OK",
              "code": 200,
              "header": [
                {
                  "key": "Content-Type",
                  "value": "application/json"
                }
              ],
              "body": "{\n  \"converted\": {}\n}",
              "cookie": [],
              "_postman_previewlanguage": "json"
            },
            {
              "id": "f8f61dd6-dab8-45ec-83c4-37478fcf3e5d",
              "name": "RFC 7807 problem response",
              "originalRequest": {
                "url": {
                  "path": [
                    "convert"
                  ],
                  "host": [
                    "{{baseUrl}}"
                  ],
                  "query": [],
                  "variable": []
                },
                "header": [
                  {
                    "key": "Accept",
                    "value": "application/problem+json"
                  }
                ],
                "method": "POST",
                "body": {
                  "mode": "raw",
                  "raw": "{\n  \"asyncapi\": \"<object>\",\n  \"version\": \"<string>\",\n  \"language\": \"<string>\"\n}",
                  "options": {
                    "raw": {
                      "language": "json"
                    }
                  }
                }
              },
              "status": "Unprocessable Entity (WebDAV) (RFC 4918)",
              "code": 422,
              "header": [
                {
                  "key": "Content-Type",
                  "value": "application/problem+json"
                }
              ],
              "body": "{\n  \"type\": \"https://AvorCmBazGYDsnzuMDYNlJYkSGB.bhcmStac\",\n  \"title\": \"string\",\n  \"status\": 7198,\n  \"detail\": \"string\",\n  \"instance\": \"string\"\n}",
              "cookie": [],
              "_postman_previewlanguage": "json"
            }
          ],
          "event": [],
          "protocolProfileBehavior": {
            "disableBodyPruning": true
          }
        }
      ],
      "event": []
    },
    {
      "id": "3e5ec97b-9dfb-41ef-a4e8-a96a3e06349c",
      "name": "Generate",
      "description": {
        "content": "",
        "type": "text/plain"
      },
      "item": [
        {
          "id": "cbd17be6-b0c1-4bb4-97a4-05b7f11e38ac",
          "name": "Generate code or documentation from an AsyncAPI document",
          "request": {
            "name": "Generate code or documentation from an AsyncAPI document",
            "description": {},
            "url": {
              "path": [
                "generate"
              ],
              "host": [
                "{{baseUrl}}"
              ],
              "query": [],
              "variable": []
            },
            "header": [
              {
                "key": "Content-Type",
                "value": "application/json"
              },
              {
                "key": "Accept",
                "value": "application/zip"
              }
            ],
            "method": "POST",
            "auth": null,
            "body": {
              "mode": "raw",
              "raw": "{\n  \"asyncapi\": \"<object>\",\n  \"template\": \"<string>\",\n  \"parameters\": {\n    \"key_0\": \"string\"\n  }\n}",
              "options": {
                "raw": {
                  "language": "json"
                }
              }
            }
          },
          "response": [
            {
              "id": "7d79221a-4e19-4c36-b829-0487c336e745",
              "name": "Generated artifacts (zip)",
              "originalRequest": {
                "url": {
                  "path": [
                    "generate"
                  ],
                  "host": [
                    "{{baseUrl}}"
                  ],
                  "query": [],
                  "variable": []
                },
                "header": [
                  {
                    "key": "Accept",
                    "value": "application/zip"
                  }
                ],
                "method": "POST",
                "body": {
                  "mode": "raw",
                  "raw": "{\n  \"asyncapi\": \"<object>\",\n  \"template\": \"<string>\",\n  \"parameters\": {\n    \"key_0\": true,\n    \"key_1\": \"string\"\n  }\n}",
                  "options": {
                    "raw": {
                      "language": "json"
                    }
                  }
                }
              },
              "status": "OK",
              "code": 200,
              "header": [
                {
                  "key": "Content-Type",
                  "value": "application/zip"
                }
              ],
              "body": "string",
              "cookie": [],
              "_postman_previewlanguage": "text"
            },
            {
              "id": "3fc0aed4-4205-4927-a641-510a7fcd4066",
              "name": "RFC 7807 problem response",
              "originalRequest": {
                "url": {
                  "path": [
                    "generate"
                  ],
                  "host": [
                    "{{baseUrl}}"
                  ],
                  "query": [],
                  "variable": []
                },
                "header": [
                  {
                    "key": "Accept",
                    "value": "application/problem+json"
                  }
                ],
                "method": "POST",
                "body": {
                  "mode": "raw",
                  "raw": "{\n  \"asyncapi\": \"<object>\",\n  \"template\": \"<string>\",\n  \"parameters\": {\n    \"key_0\": true,\n    \"key_1\": \"string\"\n  }\n}",
                  "options": {
                    "raw": {
                      "language": "json"
                    }
                  }
                }
              },
              "status": "Unprocessable Entity (WebDAV) (RFC 4918)",
              "code": 422,
              "header": [
                {
                  "key": "Content-Type",
                  "value": "application/problem+json"
                }
              ],
              "body": "{\n  \"type\": \"https://AvorCmBazGYDsnzuMDYNlJYkSGB.bhcmStac\",\n  \"title\": \"string\",\n  \"status\": 7198,\n  \"detail\": \"string\",\n  \"instance\": \"string\"\n}",
              "cookie": [],
              "_postman_previewlanguage": "json"
            }
          ],
          "event": [],
          "protocolProfileBehavior": {
            "disableBodyPruning": true
          }
        }
      ],
      "event": []
    },
    {
      "id": "46cbea85-2d05-4ab4-b25d-a2706724920a",
      "name": "Bundle",
      "description": {
        "content": "",
        "type": "text/plain"
      },
      "item": [
        {
          "id": "4830fba3-7ff3-4a7b-a5ff-e6b01c32e88d",
          "name": "Bundle multiple AsyncAPI documents",
          "request": {
            "name": "Bundle multiple AsyncAPI documents",
            "description": {},
            "url": {
              "path": [
                "bundle"
              ],
              "host": [
                "{{baseUrl}}"
              ],
              "query": [],
              "variable": []
            },
            "header": [
              {
                "key": "Content-Type",
                "value": "application/json"
              },
              {
                "key": "Accept",
                "value": "application/json"
              }
            ],
            "method": "POST",
            "auth": null,
            "body": {
              "mode": "raw",
              "raw": "{\n  \"asyncapis\": [\n    \"<object>\",\n    \"<object>\"\n  ],\n  \"base\": \"<object>\"\n}",
              "options": {
                "raw": {
                  "language": "json"
                }
              }
            }
          },
          "response": [
            {
              "id": "ec1fd449-5447-4f62-b313-85d6b7a00b4a",
              "name": "Bundled document",
              "originalRequest": {
                "url": {
                  "path": [
                    "bundle"
                  ],
                  "host": [
                    "{{baseUrl}}"
                  ],
                  "query": [],
                  "variable": []
                },
                "header": [
                  {
                    "key": "Accept",
                    "value": "application/json"
                  }
                ],
                "method": "POST",
                "body": {
                  "mode": "raw",
                  "raw": "{\n  \"asyncapis\": [\n    \"<object>\",\n    \"<object>\"\n  ],\n  \"base\": \"<object>\"\n}",
                  "options": {
                    "raw": {
                      "language": "json"
                    }
                  }
                }
              },
              "status": "OK",
              "code": 200,
              "header": [
                {
                  "key": "Content-Type",
                  "value": "application/json"
                }
              ],
              "body": "{\n  \"bundled\": {}\n}",
              "cookie": [],
              "_postman_previewlanguage": "json"
            },
            {
              "id": "9b8524f0-1881-431d-aaa1-dd33513e9d33",
              "name": "RFC 7807 problem response",
              "originalRequest": {
                "url": {
                  "path": [
                    "bundle"
                  ],
                  "host": [
                    "{{baseUrl}}"
                  ],
                  "query": [],
                  "variable": []
                },
                "header": [
                  {
                    "key": "Accept",
                    "value": "application/problem+json"
                  }
                ],
                "method": "POST",
                "body": {
                  "mode": "raw",
                  "raw": "{\n  \"asyncapis\": [\n    \"<object>\",\n    \"<object>\"\n  ],\n  \"base\": \"<object>\"\n}",
                  "options": {
                    "raw": {
                      "language": "json"
                    }
                  }
                }
              },
              "status": "Unprocessable Entity (WebDAV) (RFC 4918)",
              "code": 422,
              "header": [
                {
                  "key": "Content-Type",
                  "value": "application/problem+json"
                }
              ],
              "body": "{\n  \"type\": \"https://AvorCmBazGYDsnzuMDYNlJYkSGB.bhcmStac\",\n  \"title\": \"string\",\n  \"status\": 7198,\n  \"detail\": \"string\",\n  \"instance\": \"string\"\n}",
              "cookie": [],
              "_postman_previewlanguage": "json"
            }
          ],
          "event": [],
          "protocolProfileBehavior": {
            "disableBodyPruning": true
          }
        }
      ],
      "event": []
    },
    {
      "id": "059cecc0-157f-4b80-84e1-c3fd1db8acfb",
      "name": "Diff",
      "description": {
        "content": "",
        "type": "text/plain"
      },
      "item": [
        {
          "id": "32aa494d-5afa-4f83-ac78-83a3c24e3ad3",
          "name": "Diff two AsyncAPI documents",
          "request": {
            "name": "Diff two AsyncAPI documents",
            "description": {},
            "url": {
              "path": [
                "diff"
              ],
              "host": [
                "{{baseUrl}}"
              ],
              "query": [],
              "variable": []
            },
            "header": [
              {
                "key": "Content-Type",
                "value": "application/json"
              },
              {
                "key": "Accept",
                "value": "application/json"
              }
            ],
            "method": "POST",
            "auth": null,
            "body": {
              "mode": "raw",
              "raw": "{\n  \"asyncapis\": [\n    \"<object>\",\n    \"<object>\"\n  ]\n}",
              "options": {
                "raw": {
                  "language": "json"
                }
              }
            }
          },
          "response": [
            {
              "id": "6a0205ed-392e-40f2-86d6-2573d8d3c76f",
              "name": "Diff result",
              "originalRequest": {
                "url": {
                  "path": [
                    "diff"
                  ],
                  "host": [
                    "{{baseUrl}}"
                  ],
                  "query": [],
                  "variable": []
                },
                "header": [
                  {
                    "key": "Accept",
                    "value": "application/json"
                  }
                ],
                "method": "POST",
                "body": {
                  "mode": "raw",
                  "raw": "{\n  \"asyncapis\": [\n    \"<object>\",\n    \"<object>\"\n  ]\n}",
                  "options": {
                    "raw": {
                      "language": "json"
                    }
                  }
                }
              },
              "status": "OK",
              "code": 200,
              "header": [
                {
                  "key": "Content-Type",
                  "value": "application/json"
                }
              ],
              "body": "{\n  \"diff\": {}\n}",
              "cookie": [],
              "_postman_previewlanguage": "json"
            },
            {
              "id": "ca52e2dc-1054-4fa1-a21e-d2e148aa1cf8",
              "name": "RFC 7807 problem response",
              "originalRequest": {
                "url": {
                  "path": [
                    "diff"
                  ],
                  "host": [
                    "{{baseUrl}}"
                  ],
                  "query": [],
                  "variable": []
                },
                "header": [
                  {
                    "key": "Accept",
                    "value": "application/problem+json"
                  }
                ],
                "method": "POST",
                "body": {
                  "mode": "raw",
                  "raw": "{\n  \"asyncapis\": [\n    \"<object>\",\n    \"<object>\"\n  ]\n}",
                  "options": {
                    "raw": {
                      "language": "json"
                    }
                  }
                }
              },
              "status": "Unprocessable Entity (WebDAV) (RFC 4918)",
              "code": 422,
              "header": [
                {
                  "key": "Content-Type",
                  "value": "application/problem+json"
                }
              ],
              "body": "{\n  \"type\": \"https://AvorCmBazGYDsnzuMDYNlJYkSGB.bhcmStac\",\n  \"title\": \"string\",\n  \"status\": 7198,\n  \"detail\": \"string\",\n  \"instance\": \"string\"\n}",
              "cookie": [],
              "_postman_previewlanguage": "json"
            }
          ],
          "event": [],
          "protocolProfileBehavior": {
            "disableBodyPruning": true
          }
        }
      ],
      "event": []
    },
    {
      "id": "e9001256-17c4-48e3-8e53-3e0ecbbade7a",
      "name": "Help",
      "description": {
        "content": "",
        "type": "text/plain"
      },
      "item": [
        {
          "id": "6965353d-6b51-4569-98b3-785ff99571ef",
          "name": "Retrieve command and endpoint help",
          "request": {
            "name": "Retrieve command and endpoint help",
            "description": {},
            "url": {
              "path": [
                "help"
              ],
              "host": [
                "{{baseUrl}}"
              ],
              "query": [],
              "variable": []
            },
            "method": "GET",
            "auth": null
          },
          "response": [
            {
              "id": "a69160e1-d1b0-4f2f-8b1c-136909d2f1bb",
              "name": "Help payload",
              "originalRequest": {
                "url": {
                  "path": [
                    "help"
                  ],
                  "host": [
                    "{{baseUrl}}"
                  ],
                  "query": [],
                  "variable": []
                },
                "method": "GET",
                "body": {}
              },
              "status": "OK",
              "code": 200,
              "header": [
                {
                  "key": "Content-Type",
                  "value": "text/plain"
                }
              ],
              "body": "",
              "cookie": [],
              "_postman_previewlanguage": "text"
            }
          ],
          "event": [],
          "protocolProfileBehavior": {
            "disableBodyPruning": true
          }
        }
      ],
      "event": []
    }
  ],
  "event": [],
  "variable": [
    {
      "type": "string",
      "value": "http://localhost",
      "key": "baseUrl"
    }
  ],
  "info": {
    "_postman_id": "609d5cf6-cb99-449d-b479-f24a655db745",
    "name": "AsyncAPI Server API",
    "schema": "https://schema.getpostman.com/json/collection/v2.1.0/collection.json",
    "description": {
      "content": "The AsyncAPI Server API exposes the official AsyncAPI tooling\n(validation, parsing, conversion, code generation, bundling, diffing)\nover HTTP. It is open source under the AsyncAPI Initiative (now part of\nthe AsyncAPI CLI repository) and can be self-hosted via Docker.\n\nNote: The AsyncAPI specification itself is a documentation/specification\nstandard, not an API. This document covers the companion AsyncAPI Server\nAPI which provides the runtime HTTP surface.\n\n\nContact Support:\n Name: AsyncAPI Initiative",
      "type": "text/plain"
    }
  }
}